{
    "boxShadow": "none",
    "mobileBottomRow": 109,
    "widgetName": "Image1",
    "displayName": "Image",
    "iconSVG": "/static/media/icon.69b0f0dd810281fbd6e34fc2c3f39344.svg",
    "topRow": 97,
    "bottomRow": 109,
    "parentRowSpace": 10,
    "type": "IMAGE_WIDGET",
    "hideCard": false,
    "mobileRightColumn": 46,
    "animateLoading": true,
    "parentColumnSpace": 11.796875,
    "dynamicTriggerPathList": [],
    "imageShape": "RECTANGLE",
    "leftColumn": 34,
    "dynamicBindingPathList": [
        {"key": "borderRadius"},
        {"key": "image"}
    ],
    "defaultImage": "https://assets.appsmith.com/widgets/default.png",
    "flexVerticalAlignment": "start",
    "key": "bzfm5lbua4",
    "image": "{{Api9.data}}",
    "isDeprecated": false,
    "rightColumn": 46,
    "objectFit": "cover",
    "widgetId": "jsf8k4i3qt",
    "isVisible": true,
    "version": 1,
    "parentId": "0",
    "tags": ["Media"],
    "renderMode": "CANVAS",
    "isLoading": false,
    "mobileTopRow": 97,
    "maxZoomLevel": 1,
    "enableDownload": false,
    "borderRadius": "{{appsmith.theme.borderRadius.appBorderRadius}}",
    "mobileLeftColumn": 34,
    "enableRotation": false
}